book.toml
eisvogel.tex
isc_book_maker/__init__.py
isc_book_maker/clean.py
isc_book_maker/default.toml
isc_book_maker/imgprocessor.py
isc_book_maker/latex_runner.py
isc_book_maker/main.py
isc_book_maker/pandoc_runner.py
isc_book_maker/preprocessor.py
isc_book_maker/util.py
isc_book_maker-0.1.3.dist-info/METADATA
isc_book_maker-0.1.3.dist-info/WHEEL
isc_book_maker-0.1.3.dist-info/entry_points.txt
isc_book_maker-0.1.3.dist-info/RECORD
