Metadata-Version: 2.1
Name: isc-book-maker
Version: 0.1.3
Summary: 
Home-page: https://github.com/supcik/isc-book-maker
License: Apache-2
Author: Jacques Supcik
Author-email: jacques.supcik@hefr.ch
Requires-Python: >=3.11,<4.0
Classifier: License :: Other/Proprietary License
Classifier: Programming Language :: Python :: 3
Classifier: Programming Language :: Python :: 3.11
Requires-Dist: click (>=8.1.7,<9.0.0)
Requires-Dist: colorlog (>=6.7.0,<7.0.0)
Requires-Dist: deepmerge (>=1.1.0,<2.0.0)
Requires-Dist: jinja2 (>=3.1.2,<4.0.0)
Requires-Dist: psutil (>=5.9.5,<6.0.0)
Project-URL: Repository, https://github.com/supcik/isc-book-maker
